fx_python_sdk_cli/__init__.py
fx_python_sdk_cli/agreement_body.json
fx_python_sdk_cli/catalog_request_body.json
fx_python_sdk_cli/cli.py
fx_python_sdk_cli/consumer.py
fx_python_sdk_cli/consumer_cfg.yaml
fx_python_sdk_cli/provider.py
fx_python_sdk_cli/provider_cfg.yaml
fx_python_sdk_cli/utils.py
fx_python_sdk_cli-0.1.6.dist-info/LICENSE
fx_python_sdk_cli-0.1.6.dist-info/METADATA
fx_python_sdk_cli-0.1.6.dist-info/WHEEL
fx_python_sdk_cli-0.1.6.dist-info/top_level.txt
fx_python_sdk_cli-0.1.6.dist-info/RECORD
