Metadata-Version: 2.1
Name: fx-python-sdk-cli
Version: 0.1.6
Summary: Interact with FX Port to share / retrieve AAS Submodel
Home-page: https://github.com/fvolz/fx-python-sdk-cli
Author: FX
Author-email: fx@fx.com
Classifier: Programming Language :: Python :: 3
Classifier: License :: OSI Approved :: Apache Software License
Classifier: Operating System :: OS Independent
Requires-Python: >=3.6
License-File: LICENSE
Requires-Dist: PyYAML>=6.0.2
Requires-Dist: requests>=2.32.3
